assystem-1.0.0.dist-info/METADATA
assystem-1.0.0.dist-info/WHEEL
assystem/__init__.py
assystem/assystem.cpython-39-powerpc64le-linux-gnu.so
assystem-1.0.0.dist-info/RECORD
